broadcastify_archtk/__init__.py
broadcastify_archtk/btk.py
broadcastify_archtk-1.0.2.dist-info/LICENSE
broadcastify_archtk-1.0.2.dist-info/METADATA
broadcastify_archtk-1.0.2.dist-info/WHEEL
broadcastify_archtk-1.0.2.dist-info/top_level.txt
broadcastify_archtk-1.0.2.dist-info/RECORD
