Metadata-Version: 2.1
Name: broadcastify-archtk
Version: 1.0.2
Summary: The Broadcastify Archive Tool Kit
Home-page: https://github.com/ljhopkins2/broadcastify-archtk
Author: Joseph Hopkins
Author-email: 49728392+ljhopkins2@users.noreply.github.com
License: UNKNOWN
Platform: UNKNOWN
Classifier: Programming Language :: Python :: 3
Classifier: License :: OSI Approved :: GNU Affero General Public License v3
Classifier: Operating System :: OS Independent
Requires-Python: >=3.7
Requires-Dist: beautifulsoup4 (==4.7.1)
Requires-Dist: configparser (==3.7.4)
Requires-Dist: requests (==2.21.0)
Requires-Dist: selenium (==3.141.0)
Requires-Dist: tqdm (==4.31.1)
